fdclient/__init__.py
fdclient/client.py
fdclient-3.1.1.dist-info/METADATA
fdclient-3.1.1.dist-info/WHEEL
fdclient-3.1.1.dist-info/top_level.txt
fdclient-3.1.1.dist-info/RECORD
