Metadata-Version: 2.1
Name: fdclient
Version: 3.1.1
Summary: fastDeploy python client
Home-page: https://github.com/notAI-tech/fastDeploy
Author: BEDAPUDI PRANEETH
Author-email: praneeth@bpraneeth.com
License: MIT
Classifier: License :: OSI Approved :: MIT License
Classifier: Programming Language :: Python
Classifier: Programming Language :: Python :: 3
Classifier: Programming Language :: Python :: 3.6
Classifier: Programming Language :: Python :: Implementation :: CPython
Requires-Python: >=3.6.0
Requires-Dist: zstandard
Requires-Dist: requests
Requires-Dist: msgpack
